vaeda/PU.py
vaeda/__init__.py
vaeda/classifier.py
vaeda/cluster.py
vaeda/mk_doublets.py
vaeda/vae.py
vaeda/vaeda.py
vaeda-0.0.1.dist-info/LICENSE
vaeda-0.0.1.dist-info/METADATA
vaeda-0.0.1.dist-info/WHEEL
vaeda-0.0.1.dist-info/top_level.txt
vaeda-0.0.1.dist-info/RECORD
